magic_center/.env
magic_center/__init__.py
magic_center/__main__.py
magic_center/data_entry.py
magic_center/log/data_entry.log
magic_center/service/__init__.py
magic_center/service/math/__init__.py
magic_center/service/math/shu_xue_ti.py
magic_center/util/__init__.py
magic_center/util/magic_center_util.py
magic_center-1.1.4.dist-info/METADATA
magic_center-1.1.4.dist-info/WHEEL
magic_center-1.1.4.dist-info/entry_points.txt
magic_center-1.1.4.dist-info/RECORD
